llmize/__init__.py
llmize/base.py
llmize/config.py
llmize/callbacks/__init__.py
llmize/callbacks/adapt_temp_on_plateau.py
llmize/callbacks/early_stopping.py
llmize/callbacks/optimal_score_stopping.py
llmize/llm/__init__.py
llmize/llm/llm_call.py
llmize/llm/llm_init.py
llmize/methods/__init__.py
llmize/methods/adopro.py
llmize/methods/hlmea.py
llmize/methods/hlmsa.py
llmize/methods/opro.py
llmize/utils/__init__.py
llmize/utils/decorators.py
llmize/utils/logger.py
llmize/utils/parsing.py
llmize/utils/plotting.py
llmize/utils/pretty_print.py
llmize/utils/truncate.py
llmize-0.3.0.dist-info/licenses/LICENSE
llmize-0.3.0.dist-info/METADATA
llmize-0.3.0.dist-info/WHEEL
llmize-0.3.0.dist-info/top_level.txt
llmize-0.3.0.dist-info/RECORD
