Metadata-Version: 2.4
Name: llmize
Version: 0.3.0
Summary: A library to use Large Language Models (LLMs) as numerical optimizers
Home-page: https://github.com/rizkiokt/llmize
Author: Rizki Oktavian
Author-email: Rizki Oktavian <rizki@bwailabs.com>
License: MIT License
Project-URL: Homepage, https://github.com/rizkiokt/llmize
Project-URL: Documentation, https://llmize.readthedocs.io
Project-URL: Repository, https://github.com/rizkiokt/llmize.git
Project-URL: Bug Tracker, https://github.com/rizkiokt/llmize/issues
Keywords: llm,optimization,opro,in-context learning
Classifier: Development Status :: 3 - Alpha
Classifier: Intended Audience :: Science/Research
Classifier: License :: OSI Approved :: MIT License
Classifier: Programming Language :: Python :: 3
Classifier: Programming Language :: Python :: 3.11
Classifier: Programming Language :: Python :: 3.12
Classifier: Programming Language :: Python :: 3.13
Classifier: Topic :: Scientific/Engineering :: Artificial Intelligence
Requires-Python: >=3.11
License-File: LICENSE
Requires-Dist: numpy>=1.21.0
Requires-Dist: google-genai>=1.15.0
Requires-Dist: colorama>=0.4.6
Requires-Dist: matplotlib>=3.5.0
Requires-Dist: python-dotenv>=0.19.0
Requires-Dist: toml>=0.10.2
Provides-Extra: dev
Requires-Dist: pytest>=7.0; extra == "dev"
Requires-Dist: pytest-cov>=4.0; extra == "dev"
Requires-Dist: black>=22.0; extra == "dev"
Requires-Dist: isort>=5.0; extra == "dev"
Requires-Dist: flake8>=5.0; extra == "dev"
Requires-Dist: mypy>=1.0; extra == "dev"
Dynamic: author
Dynamic: home-page
Dynamic: license-file
Dynamic: requires-python
